repro_tarfile/__init__.py
repro_tarfile/__init__.pyi
repro_tarfile/py.typed
repro_tarfile-0.2.0.dist-info/METADATA
repro_tarfile-0.2.0.dist-info/WHEEL
repro_tarfile-0.2.0.dist-info/licenses/LICENSE
repro_tarfile-0.2.0.dist-info/RECORD
